[
  {
    "average_return_pct": 0.0,
    "best_return_pct": 0.0,
    "created_at": "2026-05-14T00:16:46+00:00",
    "entry_delay": "30m",
    "exit_horizon": "8h",
    "id": 4527,
    "lesson": "Weak Overextended Pump: 30m to 8h needs more samples before changing rules.",
    "median_return_pct": 0.0,
    "positive_rate": 0.0,
    "sample_count": 1,
    "source_label": "Weak Overextended Pump",
    "verdict": "Too Small Sample",
    "worst_return_pct": 0.0
  },
  {
    "average_return_pct": 0.0,
    "best_return_pct": 0.0,
    "created_at": "2026-05-14T00:16:46+00:00",
    "entry_delay": "30m",
    "exit_horizon": "4h",
    "id": 4526,
    "lesson": "Weak Overextended Pump: 30m to 4h needs more samples before changing rules.",
    "median_return_pct": 0.0,
    "positive_rate": 0.0,
    "sample_count": 1,
    "source_label": "Weak Overextended Pump",
    "verdict": "Too Small Sample",
    "worst_return_pct": 0.0
  },
  {
    "average_return_pct": 0.0,
    "best_return_pct": 0.0,
    "created_at": "2026-05-14T00:16:46+00:00",
    "entry_delay": "30m",
    "exit_horizon": "2h",
    "id": 4525,
    "lesson": "Weak Overextended Pump: 30m to 2h needs more samples before changing rules.",
    "median_return_pct": 0.0,
    "positive_rate": 0.0,
    "sample_count": 1,
    "source_label": "Weak Overextended Pump",
    "verdict": "Too Small Sample",
    "worst_return_pct": 0.0
  },
  {
    "average_return_pct": -3.286713286713294,
    "best_return_pct": -3.286713286713294,
    "created_at": "2026-05-14T00:16:46+00:00",
    "entry_delay": "30m",
    "exit_horizon": "24h",
    "id": 4524,
    "lesson": "Weak Overextended Pump: 30m to 24h needs more samples before changing rules.",
    "median_return_pct": -3.286713286713294,
    "positive_rate": 0.0,
    "sample_count": 1,
    "source_label": "Weak Overextended Pump",
    "verdict": "Too Small Sample",
    "worst_return_pct": -3.286713286713294
  },
  {
    "average_return_pct": 0.0,
    "best_return_pct": 0.0,
    "created_at": "2026-05-14T00:16:46+00:00",
    "entry_delay": "30m",
    "exit_horizon": "1h",
    "id": 4523,
    "lesson": "Weak Overextended Pump: 30m to 1h needs more samples before changing rules.",
    "median_return_pct": 0.0,
    "positive_rate": 0.0,
    "sample_count": 1,
    "source_label": "Weak Overextended Pump",
    "verdict": "Too Small Sample",
    "worst_return_pct": 0.0
  },
  {
    "average_return_pct": 0.0,
    "best_return_pct": 0.0,
    "created_at": "2026-05-14T00:16:46+00:00",
    "entry_delay": "1h",
    "exit_horizon": "8h",
    "id": 4522,
    "lesson": "Weak Overextended Pump: 1h to 8h needs more samples before changing rules.",
    "median_return_pct": 0.0,
    "positive_rate": 0.0,
    "sample_count": 1,
    "source_label": "Weak Overextended Pump",
    "verdict": "Too Small Sample",
    "worst_return_pct": 0.0
  },
  {
    "average_return_pct": 0.0,
    "best_return_pct": 0.0,
    "created_at": "2026-05-14T00:16:46+00:00",
    "entry_delay": "1h",
    "exit_horizon": "4h",
    "id": 4521,
    "lesson": "Weak Overextended Pump: 1h to 4h needs more samples before changing rules.",
    "median_return_pct": 0.0,
    "positive_rate": 0.0,
    "sample_count": 1,
    "source_label": "Weak Overextended Pump",
    "verdict": "Too Small Sample",
    "worst_return_pct": 0.0
  },
  {
    "average_return_pct": 0.0,
    "best_return_pct": 0.0,
    "created_at": "2026-05-14T00:16:46+00:00",
    "entry_delay": "1h",
    "exit_horizon": "2h",
    "id": 4520,
    "lesson": "Weak Overextended Pump: 1h to 2h needs more samples before changing rules.",
    "median_return_pct": 0.0,
    "positive_rate": 0.0,
    "sample_count": 1,
    "source_label": "Weak Overextended Pump",
    "verdict": "Too Small Sample",
    "worst_return_pct": 0.0
  },
  {
    "average_return_pct": -3.286713286713294,
    "best_return_pct": -3.286713286713294,
    "created_at": "2026-05-14T00:16:46+00:00",
    "entry_delay": "1h",
    "exit_horizon": "24h",
    "id": 4519,
    "lesson": "Weak Overextended Pump: 1h to 24h needs more samples before changing rules.",
    "median_return_pct": -3.286713286713294,
    "positive_rate": 0.0,
    "sample_count": 1,
    "source_label": "Weak Overextended Pump",
    "verdict": "Too Small Sample",
    "worst_return_pct": -3.286713286713294
  },
  {
    "average_return_pct": 0.0,
    "best_return_pct": 0.0,
    "created_at": "2026-05-14T00:16:46+00:00",
    "entry_delay": "15m",
    "exit_horizon": "8h",
    "id": 4518,
    "lesson": "Weak Overextended Pump: 15m to 8h needs more samples before changing rules.",
    "median_return_pct": 0.0,
    "positive_rate": 0.0,
    "sample_count": 1,
    "source_label": "Weak Overextended Pump",
    "verdict": "Too Small Sample",
    "worst_return_pct": 0.0
  },
  {
    "average_return_pct": 0.0,
    "best_return_pct": 0.0,
    "created_at": "2026-05-14T00:16:46+00:00",
    "entry_delay": "15m",
    "exit_horizon": "4h",
    "id": 4517,
    "lesson": "Weak Overextended Pump: 15m to 4h needs more samples before changing rules.",
    "median_return_pct": 0.0,
    "positive_rate": 0.0,
    "sample_count": 1,
    "source_label": "Weak Overextended Pump",
    "verdict": "Too Small Sample",
    "worst_return_pct": 0.0
  },
  {
    "average_return_pct": 0.0,
    "best_return_pct": 0.0,
    "created_at": "2026-05-14T00:16:46+00:00",
    "entry_delay": "15m",
    "exit_horizon": "30m",
    "id": 4516,
    "lesson": "Weak Overextended Pump: 15m to 30m needs more samples before changing rules.",
    "median_return_pct": 0.0,
    "positive_rate": 0.0,
    "sample_count": 1,
    "source_label": "Weak Overextended Pump",
    "verdict": "Too Small Sample",
    "worst_return_pct": 0.0
  },
  {
    "average_return_pct": 0.0,
    "best_return_pct": 0.0,
    "created_at": "2026-05-14T00:16:46+00:00",
    "entry_delay": "15m",
    "exit_horizon": "2h",
    "id": 4515,
    "lesson": "Weak Overextended Pump: 15m to 2h needs more samples before changing rules.",
    "median_return_pct": 0.0,
    "positive_rate": 0.0,
    "sample_count": 1,
    "source_label": "Weak Overextended Pump",
    "verdict": "Too Small Sample",
    "worst_return_pct": 0.0
  },
  {
    "average_return_pct": -3.286713286713294,
    "best_return_pct": -3.286713286713294,
    "created_at": "2026-05-14T00:16:46+00:00",
    "entry_delay": "15m",
    "exit_horizon": "24h",
    "id": 4514,
    "lesson": "Weak Overextended Pump: 15m to 24h needs more samples before changing rules.",
    "median_return_pct": -3.286713286713294,
    "positive_rate": 0.0,
    "sample_count": 1,
    "source_label": "Weak Overextended Pump",
    "verdict": "Too Small Sample",
    "worst_return_pct": -3.286713286713294
  },
  {
    "average_return_pct": 0.0,
    "best_return_pct": 0.0,
    "created_at": "2026-05-14T00:16:46+00:00",
    "entry_delay": "15m",
    "exit_horizon": "1h",
    "id": 4513,
    "lesson": "Weak Overextended Pump: 15m to 1h needs more samples before changing rules.",
    "median_return_pct": 0.0,
    "positive_rate": 0.0,
    "sample_count": 1,
    "source_label": "Weak Overextended Pump",
    "verdict": "Too Small Sample",
    "worst_return_pct": 0.0
  },
  {
    "average_return_pct": -5.822515486095213,
    "best_return_pct": 109.04422726519796,
    "created_at": "2026-05-14T00:16:46+00:00",
    "entry_delay": "30m",
    "exit_horizon": "8h",
    "id": 4512,
    "lesson": "Watchlist: waiting 30m did not protect the setup by 8h; keep stricter survival rules.",
    "median_return_pct": -0.06364562118126305,
    "positive_rate": 0.20833333333333334,
    "sample_count": 48,
    "source_label": "Watchlist",
    "verdict": "Delay Fails",
    "worst_return_pct": -74.01091405184175
  },
  {
    "average_return_pct": 4.341448752953157,
    "best_return_pct": 521.6216216216217,
    "created_at": "2026-05-14T00:16:46+00:00",
    "entry_delay": "30m",
    "exit_horizon": "4h",
    "id": 4511,
    "lesson": "Watchlist: waiting 30m did not protect the setup by 4h; keep stricter survival rules.",
    "median_return_pct": -1.5605190884553866,
    "positive_rate": 0.24,
    "sample_count": 50,
    "source_label": "Watchlist",
    "verdict": "Delay Fails",
    "worst_return_pct": -58.694029850746276
  },
  {
    "average_return_pct": -2.6307331810829426,
    "best_return_pct": 40.74074074074075,
    "created_at": "2026-05-14T00:16:46+00:00",
    "entry_delay": "30m",
    "exit_horizon": "2h",
    "id": 4510,
    "lesson": "Watchlist: waiting 30m did not protect the setup by 2h; keep stricter survival rules.",
    "median_return_pct": 0.0,
    "positive_rate": 0.13725490196078433,
    "sample_count": 51,
    "source_label": "Watchlist",
    "verdict": "Delay Fails",
    "worst_return_pct": -56.59962287869264
  },
  {
    "average_return_pct": -13.294314377552501,
    "best_return_pct": 62.351261304140905,
    "created_at": "2026-05-14T00:16:46+00:00",
    "entry_delay": "30m",
    "exit_horizon": "24h",
    "id": 4509,
    "lesson": "Watchlist: waiting 30m did not protect the setup by 24h; keep stricter survival rules.",
    "median_return_pct": -3.98667957806787,
    "positive_rate": 0.2727272727272727,
    "sample_count": 44,
    "source_label": "Watchlist",
    "verdict": "Delay Fails",
    "worst_return_pct": -93.84978001257072
  },
  {
    "average_return_pct": 5.559340886531177,
    "best_return_pct": 521.6216216216217,
    "created_at": "2026-05-14T00:16:46+00:00",
    "entry_delay": "30m",
    "exit_horizon": "1h",
    "id": 4508,
    "lesson": "Watchlist: waiting 30m did not protect the setup by 1h; keep stricter survival rules.",
    "median_return_pct": 0.0,
    "positive_rate": 0.15384615384615385,
    "sample_count": 52,
    "source_label": "Watchlist",
    "verdict": "Delay Fails",
    "worst_return_pct": -56.59962287869264
  },
  {
    "average_return_pct": 0.28059749724395366,
    "best_return_pct": 116.24400274160385,
    "created_at": "2026-05-14T00:16:46+00:00",
    "entry_delay": "1h",
    "exit_horizon": "8h",
    "id": 4507,
    "lesson": "Watchlist: waiting 1h did not protect the setup by 8h; keep stricter survival rules.",
    "median_return_pct": -0.41437058941913296,
    "positive_rate": 0.4583333333333333,
    "sample_count": 48,
    "source_label": "Watchlist",
    "verdict": "Delay Fails",
    "worst_return_pct": -83.91304347826087
  },
  {
    "average_return_pct": -0.41565826063791,
    "best_return_pct": 77.40429505135388,
    "created_at": "2026-05-14T00:16:46+00:00",
    "entry_delay": "1h",
    "exit_horizon": "4h",
    "id": 4506,
    "lesson": "Watchlist: waiting 1h did not protect the setup by 4h; keep stricter survival rules.",
    "median_return_pct": 0.0,
    "positive_rate": 0.17647058823529413,
    "sample_count": 51,
    "source_label": "Watchlist",
    "verdict": "Delay Fails",
    "worst_return_pct": -58.694029850746276
  },
  {
    "average_return_pct": 2.5500651498926095,
    "best_return_pct": 37.137397950321336,
    "created_at": "2026-05-14T00:16:46+00:00",
    "entry_delay": "1h",
    "exit_horizon": "2h",
    "id": 4505,
    "lesson": "Watchlist: waiting 1h did not protect the setup by 2h; keep stricter survival rules.",
    "median_return_pct": 0.0,
    "positive_rate": 0.27450980392156865,
    "sample_count": 51,
    "source_label": "Watchlist",
    "verdict": "Delay Fails",
    "worst_return_pct": -83.91304347826087
  },
  {
    "average_return_pct": -10.21545264780246,
    "best_return_pct": 35.54701792901574,
    "created_at": "2026-05-14T00:16:46+00:00",
    "entry_delay": "1h",
    "exit_horizon": "24h",
    "id": 4504,
    "lesson": "Watchlist: waiting 1h did not protect the setup by 24h; keep stricter survival rules.",
    "median_return_pct": -0.4134435849559859,
    "positive_rate": 0.2222222222222222,
    "sample_count": 45,
    "source_label": "Watchlist",
    "verdict": "Delay Fails",
    "worst_return_pct": -85.8291093410572
  },
  {
    "average_return_pct": -1.7445733514587023,
    "best_return_pct": 109.04422726519796,
    "created_at": "2026-05-14T00:16:46+00:00",
    "entry_delay": "15m",
    "exit_horizon": "8h",
    "id": 4503,
    "lesson": "Watchlist: waiting 15m did not protect the setup by 8h; keep stricter survival rules.",
    "median_return_pct": -0.5389392499370427,
    "positive_rate": 0.4166666666666667,
    "sample_count": 48,
    "source_label": "Watchlist",
    "verdict": "Delay Fails",
    "worst_return_pct": -83.91304347826087
  },
  {
    "average_return_pct": -2.615898670743381,
    "best_return_pct": 18.355973528387317,
    "created_at": "2026-05-14T00:16:46+00:00",
    "entry_delay": "15m",
    "exit_horizon": "4h",
    "id": 4502,
    "lesson": "Watchlist: waiting 15m did not protect the setup by 4h; keep stricter survival rules.",
    "median_return_pct": 0.0,
    "positive_rate": 0.17647058823529413,
    "sample_count": 51,
    "source_label": "Watchlist",
    "verdict": "Delay Fails",
    "worst_return_pct": -58.694029850746276
  },
  {
    "average_return_pct": 3.9402566186681227,
    "best_return_pct": 37.137397950321336,
    "created_at": "2026-05-14T00:16:46+00:00",
    "entry_delay": "15m",
    "exit_horizon": "30m",
    "id": 4501,
    "lesson": "Watchlist: waiting 15m did not protect the setup by 30m; keep stricter survival rules.",
    "median_return_pct": 0.0,
    "positive_rate": 0.21153846153846154,
    "sample_count": 52,
    "source_label": "Watchlist",
    "verdict": "Delay Fails",
    "worst_return_pct": -83.91304347826087
  },
  {
    "average_return_pct": 1.2247174761240232,
    "best_return_pct": 40.74074074074075,
    "created_at": "2026-05-14T00:16:46+00:00",
    "entry_delay": "15m",
    "exit_horizon": "2h",
    "id": 4500,
    "lesson": "Watchlist: waiting 15m did not protect the setup by 2h; keep stricter survival rules.",
    "median_return_pct": 0.0,
    "positive_rate": 0.3333333333333333,
    "sample_count": 51,
    "source_label": "Watchlist",
    "verdict": "Delay Fails",
    "worst_return_pct": -83.91304347826087
  },
  {
    "average_return_pct": -10.954701489838671,
    "best_return_pct": 35.54701792901574,
    "created_at": "2026-05-14T00:16:46+00:00",
    "entry_delay": "15m",
    "exit_horizon": "24h",
    "id": 4499,
    "lesson": "Watchlist: waiting 15m did not protect the setup by 24h; keep stricter survival rules.",
    "median_return_pct": -0.4134435849559859,
    "positive_rate": 0.2222222222222222,
    "sample_count": 45,
    "source_label": "Watchlist",
    "verdict": "Delay Fails",
    "worst_return_pct": -93.84978001257072
  },
  {
    "average_return_pct": -1.1076714379120953,
    "best_return_pct": 40.74074074074075,
    "created_at": "2026-05-14T00:16:46+00:00",
    "entry_delay": "15m",
    "exit_horizon": "1h",
    "id": 4498,
    "lesson": "Watchlist: waiting 15m did not protect the setup by 1h; keep stricter survival rules.",
    "median_return_pct": 0.0,
    "positive_rate": 0.09433962264150944,
    "sample_count": 53,
    "source_label": "Watchlist",
    "verdict": "Delay Fails",
    "worst_return_pct": -56.59962287869264
  },
  {
    "average_return_pct": 7.945925980747153,
    "best_return_pct": 74.00286032099157,
    "created_at": "2026-05-14T00:16:46+00:00",
    "entry_delay": "30m",
    "exit_horizon": "8h",
    "id": 4497,
    "lesson": "Research Candidate: waiting 30m did not protect the setup by 8h; keep stricter survival rules.",
    "median_return_pct": 0.0,
    "positive_rate": 0.4666666666666667,
    "sample_count": 15,
    "source_label": "Research Candidate",
    "verdict": "Delay Fails",
    "worst_return_pct": -51.67571018193424
  },
  {
    "average_return_pct": -4.440874066484187,
    "best_return_pct": 32.20829315332689,
    "created_at": "2026-05-14T00:16:46+00:00",
    "entry_delay": "30m",
    "exit_horizon": "4h",
    "id": 4496,
    "lesson": "Research Candidate: 30m to 4h needs more samples before changing rules.",
    "median_return_pct": -0.1232032854209586,
    "positive_rate": 0.4,
    "sample_count": 15,
    "source_label": "Research Candidate",
    "verdict": "Mixed Delay",
    "worst_return_pct": -48.13278008298756
  },
  {
    "average_return_pct": 0.20465336789733107,
    "best_return_pct": 42.52651880424301,
    "created_at": "2026-05-14T00:16:46+00:00",
    "entry_delay": "30m",
    "exit_horizon": "2h",
    "id": 4495,
    "lesson": "Research Candidate: 30m to 2h needs more samples before changing rules.",
    "median_return_pct": 0.0,
    "positive_rate": 0.13333333333333333,
    "sample_count": 15,
    "source_label": "Research Candidate",
    "verdict": "Mixed Delay",
    "worst_return_pct": -37.631662942866264
  },
  {
    "average_return_pct": -16.785092853246088,
    "best_return_pct": 25.393367223432573,
    "created_at": "2026-05-14T00:16:46+00:00",
    "entry_delay": "30m",
    "exit_horizon": "24h",
    "id": 4494,
    "lesson": "Research Candidate: waiting 30m did not protect the setup by 24h; keep stricter survival rules.",
    "median_return_pct": -2.408348943002414,
    "positive_rate": 0.3076923076923077,
    "sample_count": 13,
    "source_label": "Research Candidate",
    "verdict": "Delay Fails",
    "worst_return_pct": -92.40983083306735
  },
  {
    "average_return_pct": -5.910979096777367,
    "best_return_pct": 2.4570321955942775,
    "created_at": "2026-05-14T00:16:46+00:00",
    "entry_delay": "30m",
    "exit_horizon": "1h",
    "id": 4493,
    "lesson": "Research Candidate: 30m to 1h needs more samples before changing rules.",
    "median_return_pct": 0.0,
    "positive_rate": 0.06666666666666667,
    "sample_count": 15,
    "source_label": "Research Candidate",
    "verdict": "Mixed Delay",
    "worst_return_pct": -37.69549952122566
  },
  {
    "average_return_pct": 14.15030414315709,
    "best_return_pct": 74.00286032099157,
    "created_at": "2026-05-14T00:16:46+00:00",
    "entry_delay": "1h",
    "exit_horizon": "8h",
    "id": 4492,
    "lesson": "Research Candidate: waiting 1h still held up into 8h; compare with baselines.",
    "median_return_pct": 7.708049113233284,
    "positive_rate": 0.6666666666666666,
    "sample_count": 15,
    "source_label": "Research Candidate",
    "verdict": "Promising Delay",
    "worst_return_pct": -22.438524590163933
  },
  {
    "average_return_pct": 1.1143607591925502,
    "best_return_pct": 32.20829315332689,
    "created_at": "2026-05-14T00:16:46+00:00",
    "entry_delay": "1h",
    "exit_horizon": "4h",
    "id": 4491,
    "lesson": "Research Candidate: 1h to 4h needs more samples before changing rules.",
    "median_return_pct": 0.49798115746972904,
    "positive_rate": 0.5333333333333333,
    "sample_count": 15,
    "source_label": "Research Candidate",
    "verdict": "Mixed Delay",
    "worst_return_pct": -16.752049180327877
  },
  {
    "average_return_pct": 6.971952809763885,
    "best_return_pct": 42.52651880424301,
    "created_at": "2026-05-14T00:16:46+00:00",
    "entry_delay": "1h",
    "exit_horizon": "2h",
    "id": 4490,
    "lesson": "Research Candidate: 1h to 2h needs more samples before changing rules.",
    "median_return_pct": 0.0,
    "positive_rate": 0.4,
    "sample_count": 15,
    "source_label": "Research Candidate",
    "verdict": "Mixed Delay",
    "worst_return_pct": -4.068012076910854
  },
  {
    "average_return_pct": -12.368432568818289,
    "best_return_pct": 22.38629651506201,
    "created_at": "2026-05-14T00:16:46+00:00",
    "entry_delay": "1h",
    "exit_horizon": "24h",
    "id": 4489,
    "lesson": "Research Candidate: waiting 1h did not protect the setup by 24h; keep stricter survival rules.",
    "median_return_pct": 0.0,
    "positive_rate": 0.46153846153846156,
    "sample_count": 13,
    "source_label": "Research Candidate",
    "verdict": "Delay Fails",
    "worst_return_pct": -87.81762295081967
  },
  {
    "average_return_pct": 12.316638434580401,
    "best_return_pct": 74.00286032099157,
    "created_at": "2026-05-14T00:16:46+00:00",
    "entry_delay": "15m",
    "exit_horizon": "8h",
    "id": 4488,
    "lesson": "Research Candidate: waiting 15m did not protect the setup by 8h; keep stricter survival rules.",
    "median_return_pct": 7.708049113233284,
    "positive_rate": 0.7333333333333333,
    "sample_count": 15,
    "source_label": "Research Candidate",
    "verdict": "Delay Fails",
    "worst_return_pct": -51.67571018193424
  },
  {
    "average_return_pct": -0.871980296148265,
    "best_return_pct": 32.20829315332689,
    "created_at": "2026-05-14T00:16:46+00:00",
    "entry_delay": "15m",
    "exit_horizon": "4h",
    "id": 4487,
    "lesson": "Research Candidate: 15m to 4h needs more samples before changing rules.",
    "median_return_pct": 0.49798115746972904,
    "positive_rate": 0.5333333333333333,
    "sample_count": 15,
    "source_label": "Research Candidate",
    "verdict": "Mixed Delay",
    "worst_return_pct": -48.13278008298756
  },
  {
    "average_return_pct": 4.370712453833249,
    "best_return_pct": 37.137397950321336,
    "created_at": "2026-05-14T00:16:46+00:00",
    "entry_delay": "15m",
    "exit_horizon": "30m",
    "id": 4486,
    "lesson": "Research Candidate: 15m to 30m needs more samples before changing rules.",
    "median_return_pct": 0.0,
    "positive_rate": 0.26666666666666666,
    "sample_count": 15,
    "source_label": "Research Candidate",
    "verdict": "Mixed Delay",
    "worst_return_pct": 0.0
  },
  {
    "average_return_pct": 4.57536582173058,
    "best_return_pct": 42.52651880424301,
    "created_at": "2026-05-14T00:16:46+00:00",
    "entry_delay": "15m",
    "exit_horizon": "2h",
    "id": 4485,
    "lesson": "Research Candidate: 15m to 2h needs more samples before changing rules.",
    "median_return_pct": 0.0,
    "positive_rate": 0.4,
    "sample_count": 15,
    "source_label": "Research Candidate",
    "verdict": "Mixed Delay",
    "worst_return_pct": -37.631662942866264
  },
  {
    "average_return_pct": -12.541022158409133,
    "best_return_pct": 25.393367223432573,
    "created_at": "2026-05-14T00:16:46+00:00",
    "entry_delay": "15m",
    "exit_horizon": "24h",
    "id": 4484,
    "lesson": "Research Candidate: waiting 15m did not protect the setup by 24h; keep stricter survival rules.",
    "median_return_pct": 0.0,
    "positive_rate": 0.46153846153846156,
    "sample_count": 13,
    "source_label": "Research Candidate",
    "verdict": "Delay Fails",
    "worst_return_pct": -92.40983083306735
  },
  {
    "average_return_pct": -2.3908074384838858,
    "best_return_pct": 2.4570321955942775,
    "created_at": "2026-05-14T00:16:46+00:00",
    "entry_delay": "15m",
    "exit_horizon": "1h",
    "id": 4483,
    "lesson": "Research Candidate: 15m to 1h needs more samples before changing rules.",
    "median_return_pct": 0.0,
    "positive_rate": 0.06666666666666667,
    "sample_count": 15,
    "source_label": "Research Candidate",
    "verdict": "Mixed Delay",
    "worst_return_pct": -37.69549952122566
  },
  {
    "average_return_pct": -0.19648596987504804,
    "best_return_pct": 10.90047393364928,
    "created_at": "2026-05-14T00:16:46+00:00",
    "entry_delay": "30m",
    "exit_horizon": "8h",
    "id": 4482,
    "lesson": "Reject: 30m to 8h needs more samples before changing rules.",
    "median_return_pct": 0.0,
    "positive_rate": 0.07352941176470588,
    "sample_count": 204,
    "source_label": "Reject",
    "verdict": "Mixed Delay",
    "worst_return_pct": -14.093959731543626
  },
  {
    "average_return_pct": -0.1360804469634424,
    "best_return_pct": 16.31685849695328,
    "created_at": "2026-05-14T00:16:46+00:00",
    "entry_delay": "30m",
    "exit_horizon": "4h",
    "id": 4481,
    "lesson": "Reject: 30m to 4h needs more samples before changing rules.",
    "median_return_pct": 0.0,
    "positive_rate": 0.0880281690140845,
    "sample_count": 284,
    "source_label": "Reject",
    "verdict": "Mixed Delay",
    "worst_return_pct": -13.066509711595053
  },
  {
    "average_return_pct": -0.051960695460216866,
    "best_return_pct": 4.731379731379737,
    "created_at": "2026-05-14T00:16:46+00:00",
    "entry_delay": "30m",
    "exit_horizon": "2h",
    "id": 4480,
    "lesson": "Reject: 30m to 2h needs more samples before changing rules.",
    "median_return_pct": 0.0,
    "positive_rate": 0.021341463414634148,
    "sample_count": 328,
    "source_label": "Reject",
    "verdict": "Mixed Delay",
    "worst_return_pct": -11.531190926275992
  },
  {
    "average_return_pct": 0.0,
    "best_return_pct": 0.0,
    "created_at": "2026-05-14T00:16:46+00:00",
    "entry_delay": "30m",
    "exit_horizon": "1h",
    "id": 4479,
    "lesson": "Reject: 30m to 1h needs more samples before changing rules.",
    "median_return_pct": 0.0,
    "positive_rate": 0.0,
    "sample_count": 357,
    "source_label": "Reject",
    "verdict": "Mixed Delay",
    "worst_return_pct": 0.0
  },
  {
    "average_return_pct": -0.19648596987504804,
    "best_return_pct": 10.90047393364928,
    "created_at": "2026-05-14T00:16:46+00:00",
    "entry_delay": "1h",
    "exit_horizon": "8h",
    "id": 4478,
    "lesson": "Reject: 1h to 8h needs more samples before changing rules.",
    "median_return_pct": 0.0,
    "positive_rate": 0.07352941176470588,
    "sample_count": 204,
    "source_label": "Reject",
    "verdict": "Mixed Delay",
    "worst_return_pct": -14.093959731543626
  },
  {
    "average_return_pct": -0.1360804469634424,
    "best_return_pct": 16.31685849695328,
    "created_at": "2026-05-14T00:16:46+00:00",
    "entry_delay": "1h",
    "exit_horizon": "4h",
    "id": 4477,
    "lesson": "Reject: 1h to 4h needs more samples before changing rules.",
    "median_return_pct": 0.0,
    "positive_rate": 0.0880281690140845,
    "sample_count": 284,
    "source_label": "Reject",
    "verdict": "Mixed Delay",
    "worst_return_pct": -13.066509711595053
  },
  {
    "average_return_pct": -0.051960695460216866,
    "best_return_pct": 4.731379731379737,
    "created_at": "2026-05-14T00:16:46+00:00",
    "entry_delay": "1h",
    "exit_horizon": "2h",
    "id": 4476,
    "lesson": "Reject: 1h to 2h needs more samples before changing rules.",
    "median_return_pct": 0.0,
    "positive_rate": 0.021341463414634148,
    "sample_count": 328,
    "source_label": "Reject",
    "verdict": "Mixed Delay",
    "worst_return_pct": -11.531190926275992
  },
  {
    "average_return_pct": -0.19648596987504804,
    "best_return_pct": 10.90047393364928,
    "created_at": "2026-05-14T00:16:46+00:00",
    "entry_delay": "15m",
    "exit_horizon": "8h",
    "id": 4475,
    "lesson": "Reject: 15m to 8h needs more samples before changing rules.",
    "median_return_pct": 0.0,
    "positive_rate": 0.07352941176470588,
    "sample_count": 204,
    "source_label": "Reject",
    "verdict": "Mixed Delay",
    "worst_return_pct": -14.093959731543626
  },
  {
    "average_return_pct": -0.1360804469634424,
    "best_return_pct": 16.31685849695328,
    "created_at": "2026-05-14T00:16:46+00:00",
    "entry_delay": "15m",
    "exit_horizon": "4h",
    "id": 4474,
    "lesson": "Reject: 15m to 4h needs more samples before changing rules.",
    "median_return_pct": 0.0,
    "positive_rate": 0.0880281690140845,
    "sample_count": 284,
    "source_label": "Reject",
    "verdict": "Mixed Delay",
    "worst_return_pct": -13.066509711595053
  },
  {
    "average_return_pct": 0.0,
    "best_return_pct": 0.0,
    "created_at": "2026-05-14T00:16:46+00:00",
    "entry_delay": "15m",
    "exit_horizon": "30m",
    "id": 4473,
    "lesson": "Reject: 15m to 30m needs more samples before changing rules.",
    "median_return_pct": 0.0,
    "positive_rate": 0.0,
    "sample_count": 358,
    "source_label": "Reject",
    "verdict": "Mixed Delay",
    "worst_return_pct": 0.0
  },
  {
    "average_return_pct": -0.051960695460216866,
    "best_return_pct": 4.731379731379737,
    "created_at": "2026-05-14T00:16:46+00:00",
    "entry_delay": "15m",
    "exit_horizon": "2h",
    "id": 4472,
    "lesson": "Reject: 15m to 2h needs more samples before changing rules.",
    "median_return_pct": 0.0,
    "positive_rate": 0.021341463414634148,
    "sample_count": 328,
    "source_label": "Reject",
    "verdict": "Mixed Delay",
    "worst_return_pct": -11.531190926275992
  },
  {
    "average_return_pct": 0.0,
    "best_return_pct": 0.0,
    "created_at": "2026-05-14T00:16:46+00:00",
    "entry_delay": "15m",
    "exit_horizon": "1h",
    "id": 4471,
    "lesson": "Reject: 15m to 1h needs more samples before changing rules.",
    "median_return_pct": 0.0,
    "positive_rate": 0.0,
    "sample_count": 357,
    "source_label": "Reject",
    "verdict": "Mixed Delay",
    "worst_return_pct": 0.0
  },
  {
    "average_return_pct": -44.995967500594,
    "best_return_pct": -2.161842882457188,
    "created_at": "2026-05-14T00:16:46+00:00",
    "entry_delay": "30m",
    "exit_horizon": "8h",
    "id": 4470,
    "lesson": "Paper Trade Candidate: 30m to 8h needs more samples before changing rules.",
    "median_return_pct": -44.995967500594,
    "positive_rate": 0.0,
    "sample_count": 2,
    "source_label": "Paper Trade Candidate",
    "verdict": "Too Small Sample",
    "worst_return_pct": -87.8300921187308
  },
  {
    "average_return_pct": -9.420193692977463,
    "best_return_pct": -6.908904810644822,
    "created_at": "2026-05-14T00:16:46+00:00",
    "entry_delay": "30m",
    "exit_horizon": "4h",
    "id": 4469,
    "lesson": "Paper Trade Candidate: 30m to 4h needs more samples before changing rules.",
    "median_return_pct": -9.420193692977463,
    "positive_rate": 0.0,
    "sample_count": 2,
    "source_label": "Paper Trade Candidate",
    "verdict": "Too Small Sample",
    "worst_return_pct": -11.931482575310104
  },
  {
    "average_return_pct": -11.411964250411561,
    "best_return_pct": -10.490253987005316,
    "created_at": "2026-05-14T00:16:46+00:00",
    "entry_delay": "30m",
    "exit_horizon": "2h",
    "id": 4468,
    "lesson": "Paper Trade Candidate: 30m to 2h needs more samples before changing rules.",
    "median_return_pct": -11.411964250411561,
    "positive_rate": 0.0,
    "sample_count": 2,
    "source_label": "Paper Trade Candidate",
    "verdict": "Too Small Sample",
    "worst_return_pct": -12.333674513817805
  },
  {
    "average_return_pct": -38.04971823892832,
    "best_return_pct": 11.730655640874165,
    "created_at": "2026-05-14T00:16:46+00:00",
    "entry_delay": "30m",
    "exit_horizon": "24h",
    "id": 4467,
    "lesson": "Paper Trade Candidate: 30m to 24h needs more samples before changing rules.",
    "median_return_pct": -38.04971823892832,
    "positive_rate": 0.5,
    "sample_count": 2,
    "source_label": "Paper Trade Candidate",
    "verdict": "Too Small Sample",
    "worst_return_pct": -87.8300921187308
  },
  {
    "average_return_pct": 0.0,
    "best_return_pct": 0.0,
    "created_at": "2026-05-14T00:16:46+00:00",
    "entry_delay": "30m",
    "exit_horizon": "1h",
    "id": 4466,
    "lesson": "Paper Trade Candidate: 30m to 1h needs more samples before changing rules.",
    "median_return_pct": 0.0,
    "positive_rate": 0.0,
    "sample_count": 2,
    "source_label": "Paper Trade Candidate",
    "verdict": "Too Small Sample",
    "worst_return_pct": 0.0
  },
  {
    "average_return_pct": -44.995967500594,
    "best_return_pct": -2.161842882457188,
    "created_at": "2026-05-14T00:16:46+00:00",
    "entry_delay": "1h",
    "exit_horizon": "8h",
    "id": 4465,
    "lesson": "Paper Trade Candidate: 1h to 8h needs more samples before changing rules.",
    "median_return_pct": -44.995967500594,
    "positive_rate": 0.0,
    "sample_count": 2,
    "source_label": "Paper Trade Candidate",
    "verdict": "Too Small Sample",
    "worst_return_pct": -87.8300921187308
  },
  {
    "average_return_pct": -9.420193692977463,
    "best_return_pct": -6.908904810644822,
    "created_at": "2026-05-14T00:16:46+00:00",
    "entry_delay": "1h",
    "exit_horizon": "4h",
    "id": 4464,
    "lesson": "Paper Trade Candidate: 1h to 4h needs more samples before changing rules.",
    "median_return_pct": -9.420193692977463,
    "positive_rate": 0.0,
    "sample_count": 2,
    "source_label": "Paper Trade Candidate",
    "verdict": "Too Small Sample",
    "worst_return_pct": -11.931482575310104
  },
  {
    "average_return_pct": -11.411964250411561,
    "best_return_pct": -10.490253987005316,
    "created_at": "2026-05-14T00:16:46+00:00",
    "entry_delay": "1h",
    "exit_horizon": "2h",
    "id": 4463,
    "lesson": "Paper Trade Candidate: 1h to 2h needs more samples before changing rules.",
    "median_return_pct": -11.411964250411561,
    "positive_rate": 0.0,
    "sample_count": 2,
    "source_label": "Paper Trade Candidate",
    "verdict": "Too Small Sample",
    "worst_return_pct": -12.333674513817805
  },
  {
    "average_return_pct": -38.04971823892832,
    "best_return_pct": 11.730655640874165,
    "created_at": "2026-05-14T00:16:46+00:00",
    "entry_delay": "1h",
    "exit_horizon": "24h",
    "id": 4462,
    "lesson": "Paper Trade Candidate: 1h to 24h needs more samples before changing rules.",
    "median_return_pct": -38.04971823892832,
    "positive_rate": 0.5,
    "sample_count": 2,
    "source_label": "Paper Trade Candidate",
    "verdict": "Too Small Sample",
    "worst_return_pct": -87.8300921187308
  },
  {
    "average_return_pct": -44.98973291663843,
    "best_return_pct": -2.161842882457188,
    "created_at": "2026-05-14T00:16:46+00:00",
    "entry_delay": "15m",
    "exit_horizon": "8h",
    "id": 4461,
    "lesson": "Paper Trade Candidate: 15m to 8h needs more samples before changing rules.",
    "median_return_pct": -44.98973291663843,
    "positive_rate": 0.0,
    "sample_count": 2,
    "source_label": "Paper Trade Candidate",
    "verdict": "Too Small Sample",
    "worst_return_pct": -87.81762295081967
  },
  {
    "average_return_pct": -9.372503582737018,
    "best_return_pct": -6.813524590163933,
    "created_at": "2026-05-14T00:16:46+00:00",
    "entry_delay": "15m",
    "exit_horizon": "4h",
    "id": 4460,
    "lesson": "Paper Trade Candidate: 15m to 4h needs more samples before changing rules.",
    "median_return_pct": -9.372503582737018,
    "positive_rate": 0.0,
    "sample_count": 2,
    "source_label": "Paper Trade Candidate",
    "verdict": "Too Small Sample",
    "worst_return_pct": -11.931482575310104
  },
  {
    "average_return_pct": 0.05122950819671512,
    "best_return_pct": 0.10245901639343025,
    "created_at": "2026-05-14T00:16:46+00:00",
    "entry_delay": "15m",
    "exit_horizon": "30m",
    "id": 4459,
    "lesson": "Paper Trade Candidate: 15m to 30m needs more samples before changing rules.",
    "median_return_pct": 0.05122950819671512,
    "positive_rate": 0.5,
    "sample_count": 2,
    "source_label": "Paper Trade Candidate",
    "verdict": "Too Small Sample",
    "worst_return_pct": 0.0
  },
  {
    "average_return_pct": -11.36705322301086,
    "best_return_pct": -10.490253987005316,
    "created_at": "2026-05-14T00:16:46+00:00",
    "entry_delay": "15m",
    "exit_horizon": "2h",
    "id": 4458,
    "lesson": "Paper Trade Candidate: 15m to 2h needs more samples before changing rules.",
    "median_return_pct": -11.36705322301086,
    "positive_rate": 0.0,
    "sample_count": 2,
    "source_label": "Paper Trade Candidate",
    "verdict": "Too Small Sample",
    "worst_return_pct": -12.243852459016402
  },
  {
    "average_return_pct": -38.04348365497275,
    "best_return_pct": 11.730655640874165,
    "created_at": "2026-05-14T00:16:46+00:00",
    "entry_delay": "15m",
    "exit_horizon": "24h",
    "id": 4457,
    "lesson": "Paper Trade Candidate: 15m to 24h needs more samples before changing rules.",
    "median_return_pct": -38.04348365497275,
    "positive_rate": 0.5,
    "sample_count": 2,
    "source_label": "Paper Trade Candidate",
    "verdict": "Too Small Sample",
    "worst_return_pct": -87.81762295081967
  },
  {
    "average_return_pct": 0.05122950819671512,
    "best_return_pct": 0.10245901639343025,
    "created_at": "2026-05-14T00:16:46+00:00",
    "entry_delay": "15m",
    "exit_horizon": "1h",
    "id": 4456,
    "lesson": "Paper Trade Candidate: 15m to 1h needs more samples before changing rules.",
    "median_return_pct": 0.05122950819671512,
    "positive_rate": 0.5,
    "sample_count": 2,
    "source_label": "Paper Trade Candidate",
    "verdict": "Too Small Sample",
    "worst_return_pct": 0.0
  },
  {
    "average_return_pct": -1.3928201989388271,
    "best_return_pct": 31.945205479452056,
    "created_at": "2026-05-14T00:16:46+00:00",
    "entry_delay": "30m",
    "exit_horizon": "8h",
    "id": 4455,
    "lesson": "Momentum Trap: 30m to 8h needs more samples before changing rules.",
    "median_return_pct": -2.603990530943523,
    "positive_rate": 0.3333333333333333,
    "sample_count": 3,
    "source_label": "Momentum Trap",
    "verdict": "Too Small Sample",
    "worst_return_pct": -33.519675545325015
  },
  {
    "average_return_pct": 69.61551697432662,
    "best_return_pct": 134.1335087142387,
    "created_at": "2026-05-14T00:16:46+00:00",
    "entry_delay": "30m",
    "exit_horizon": "4h",
    "id": 4454,
    "lesson": "Momentum Trap: 30m to 4h needs more samples before changing rules.",
    "median_return_pct": 72.01211890985404,
    "positive_rate": 1.0,
    "sample_count": 4,
    "source_label": "Momentum Trap",
    "verdict": "Too Small Sample",
    "worst_return_pct": 0.3043213633597164
  },
  {
    "average_return_pct": 28.170443016570857,
    "best_return_pct": 112.68177206628343,
    "created_at": "2026-05-14T00:16:46+00:00",
    "entry_delay": "30m",
    "exit_horizon": "2h",
    "id": 4453,
    "lesson": "Momentum Trap: 30m to 2h needs more samples before changing rules.",
    "median_return_pct": 0.0,
    "positive_rate": 0.25,
    "sample_count": 4,
    "source_label": "Momentum Trap",
    "verdict": "Too Small Sample",
    "worst_return_pct": 0.0
  },
  {
    "average_return_pct": -2.388961234142034,
    "best_return_pct": 30.410958904109584,
    "created_at": "2026-05-14T00:16:46+00:00",
    "entry_delay": "30m",
    "exit_horizon": "24h",
    "id": 4452,
    "lesson": "Momentum Trap: 30m to 24h needs more samples before changing rules.",
    "median_return_pct": -4.058167061210671,
    "positive_rate": 0.3333333333333333,
    "sample_count": 3,
    "source_label": "Momentum Trap",
    "verdict": "Too Small Sample",
    "worst_return_pct": -33.519675545325015
  },
  {
    "average_return_pct": 0.0,
    "best_return_pct": 0.0,
    "created_at": "2026-05-14T00:16:46+00:00",
    "entry_delay": "30m",
    "exit_horizon": "1h",
    "id": 4451,
    "lesson": "Momentum Trap: 30m to 1h needs more samples before changing rules.",
    "median_return_pct": 0.0,
    "positive_rate": 0.0,
    "sample_count": 4,
    "source_label": "Momentum Trap",
    "verdict": "Too Small Sample",
    "worst_return_pct": 0.0
  },
  {
    "average_return_pct": -1.3928201989388271,
    "best_return_pct": 31.945205479452056,
    "created_at": "2026-05-14T00:16:46+00:00",
    "entry_delay": "1h",
    "exit_horizon": "8h",
    "id": 4450,
    "lesson": "Momentum Trap: 1h to 8h needs more samples before changing rules.",
    "median_return_pct": -2.603990530943523,
    "positive_rate": 0.3333333333333333,
    "sample_count": 3,
    "source_label": "Momentum Trap",
    "verdict": "Too Small Sample",
    "worst_return_pct": -33.519675545325015
  },
  {
    "average_return_pct": 69.61551697432662,
    "best_return_pct": 134.1335087142387,
    "created_at": "2026-05-14T00:16:46+00:00",
    "entry_delay": "1h",
    "exit_horizon": "4h",
    "id": 4449,
    "lesson": "Momentum Trap: 1h to 4h needs more samples before changing rules.",
    "median_return_pct": 72.01211890985404,
    "positive_rate": 1.0,
    "sample_count": 4,
    "source_label": "Momentum Trap",
    "verdict": "Too Small Sample",
    "worst_return_pct": 0.3043213633597164
  },
  {
    "average_return_pct": 28.170443016570857,
    "best_return_pct": 112.68177206628343,
    "created_at": "2026-05-14T00:16:46+00:00",
    "entry_delay": "1h",
    "exit_horizon": "2h",
    "id": 4448,
    "lesson": "Momentum Trap: 1h to 2h needs more samples before changing rules.",
    "median_return_pct": 0.0,
    "positive_rate": 0.25,
    "sample_count": 4,
    "source_label": "Momentum Trap",
    "verdict": "Too Small Sample",
    "worst_return_pct": 0.0
  },
  {
    "average_return_pct": -2.388961234142034,
    "best_return_pct": 30.410958904109584,
    "created_at": "2026-05-14T00:16:46+00:00",
    "entry_delay": "1h",
    "exit_horizon": "24h",
    "id": 4447,
    "lesson": "Momentum Trap: 1h to 24h needs more samples before changing rules.",
    "median_return_pct": -4.058167061210671,
    "positive_rate": 0.3333333333333333,
    "sample_count": 3,
    "source_label": "Momentum Trap",
    "verdict": "Too Small Sample",
    "worst_return_pct": -33.519675545325015
  },
  {
    "average_return_pct": -1.3928201989388271,
    "best_return_pct": 31.945205479452056,
    "created_at": "2026-05-14T00:16:46+00:00",
    "entry_delay": "15m",
    "exit_horizon": "8h",
    "id": 4446,
    "lesson": "Momentum Trap: 15m to 8h needs more samples before changing rules.",
    "median_return_pct": -2.603990530943523,
    "positive_rate": 0.3333333333333333,
    "sample_count": 3,
    "source_label": "Momentum Trap",
    "verdict": "Too Small Sample",
    "worst_return_pct": -33.519675545325015
  },
  {
    "average_return_pct": 69.61551697432662,
    "best_return_pct": 134.1335087142387,
    "created_at": "2026-05-14T00:16:46+00:00",
    "entry_delay": "15m",
    "exit_horizon": "4h",
    "id": 4445,
    "lesson": "Momentum Trap: 15m to 4h needs more samples before changing rules.",
    "median_return_pct": 72.01211890985404,
    "positive_rate": 1.0,
    "sample_count": 4,
    "source_label": "Momentum Trap",
    "verdict": "Too Small Sample",
    "worst_return_pct": 0.3043213633597164
  },
  {
    "average_return_pct": 0.0,
    "best_return_pct": 0.0,
    "created_at": "2026-05-14T00:16:46+00:00",
    "entry_delay": "15m",
    "exit_horizon": "30m",
    "id": 4444,
    "lesson": "Momentum Trap: 15m to 30m needs more samples before changing rules.",
    "median_return_pct": 0.0,
    "positive_rate": 0.0,
    "sample_count": 4,
    "source_label": "Momentum Trap",
    "verdict": "Too Small Sample",
    "worst_return_pct": 0.0
  },
  {
    "average_return_pct": 28.170443016570857,
    "best_return_pct": 112.68177206628343,
    "created_at": "2026-05-14T00:16:46+00:00",
    "entry_delay": "15m",
    "exit_horizon": "2h",
    "id": 4443,
    "lesson": "Momentum Trap: 15m to 2h needs more samples before changing rules.",
    "median_return_pct": 0.0,
    "positive_rate": 0.25,
    "sample_count": 4,
    "source_label": "Momentum Trap",
    "verdict": "Too Small Sample",
    "worst_return_pct": 0.0
  },
  {
    "average_return_pct": -2.388961234142034,
    "best_return_pct": 30.410958904109584,
    "created_at": "2026-05-14T00:16:46+00:00",
    "entry_delay": "15m",
    "exit_horizon": "24h",
    "id": 4442,
    "lesson": "Momentum Trap: 15m to 24h needs more samples before changing rules.",
    "median_return_pct": -4.058167061210671,
    "positive_rate": 0.3333333333333333,
    "sample_count": 3,
    "source_label": "Momentum Trap",
    "verdict": "Too Small Sample",
    "worst_return_pct": -33.519675545325015
  },
  {
    "average_return_pct": 0.0,
    "best_return_pct": 0.0,
    "created_at": "2026-05-14T00:16:46+00:00",
    "entry_delay": "15m",
    "exit_horizon": "1h",
    "id": 4441,
    "lesson": "Momentum Trap: 15m to 1h needs more samples before changing rules.",
    "median_return_pct": 0.0,
    "positive_rate": 0.0,
    "sample_count": 4,
    "source_label": "Momentum Trap",
    "verdict": "Too Small Sample",
    "worst_return_pct": 0.0
  },
  {
    "average_return_pct": 9.287531806615778,
    "best_return_pct": 18.575063613231556,
    "created_at": "2026-05-14T00:16:46+00:00",
    "entry_delay": "30m",
    "exit_horizon": "8h",
    "id": 4440,
    "lesson": "High-Risk Momentum Watchlist: 30m to 8h needs more samples before changing rules.",
    "median_return_pct": 9.287531806615778,
    "positive_rate": 0.5,
    "sample_count": 2,
    "source_label": "High-Risk Momentum Watchlist",
    "verdict": "Too Small Sample",
    "worst_return_pct": 0.0
  },
  {
    "average_return_pct": 31.456743002544542,
    "best_return_pct": 62.913486005089084,
    "created_at": "2026-05-14T00:16:46+00:00",
    "entry_delay": "30m",
    "exit_horizon": "4h",
    "id": 4439,
    "lesson": "High-Risk Momentum Watchlist: 30m to 4h needs more samples before changing rules.",
    "median_return_pct": 31.456743002544542,
    "positive_rate": 0.5,
    "sample_count": 2,
    "source_label": "High-Risk Momentum Watchlist",
    "verdict": "Too Small Sample",
    "worst_return_pct": 0.0
  },
  {
    "average_return_pct": 31.456743002544542,
    "best_return_pct": 62.913486005089084,
    "created_at": "2026-05-14T00:16:46+00:00",
    "entry_delay": "30m",
    "exit_horizon": "2h",
    "id": 4438,
    "lesson": "High-Risk Momentum Watchlist: 30m to 2h needs more samples before changing rules.",
    "median_return_pct": 31.456743002544542,
    "positive_rate": 0.5,
    "sample_count": 2,
    "source_label": "High-Risk Momentum Watchlist",
    "verdict": "Too Small Sample",
    "worst_return_pct": 0.0
  },
  {
    "average_return_pct": 5.574814725496929,
    "best_return_pct": 22.328244274809173,
    "created_at": "2026-05-14T00:16:46+00:00",
    "entry_delay": "30m",
    "exit_horizon": "24h",
    "id": 4437,
    "lesson": "High-Risk Momentum Watchlist: 30m to 24h needs more samples before changing rules.",
    "median_return_pct": 5.574814725496929,
    "positive_rate": 0.5,
    "sample_count": 2,
    "source_label": "High-Risk Momentum Watchlist",
    "verdict": "Too Small Sample",
    "worst_return_pct": -11.178614823815314
  },
  {
    "average_return_pct": 31.456743002544542,
    "best_return_pct": 62.913486005089084,
    "created_at": "2026-05-14T00:16:46+00:00",
    "entry_delay": "30m",
    "exit_horizon": "1h",
    "id": 4436,
    "lesson": "High-Risk Momentum Watchlist: 30m to 1h needs more samples before changing rules.",
    "median_return_pct": 31.456743002544542,
    "positive_rate": 0.5,
    "sample_count": 2,
    "source_label": "High-Risk Momentum Watchlist",
    "verdict": "Too Small Sample",
    "worst_return_pct": 0.0
  },
  {
    "average_return_pct": -13.607965638422492,
    "best_return_pct": 0.0,
    "created_at": "2026-05-14T00:16:46+00:00",
    "entry_delay": "1h",
    "exit_horizon": "8h",
    "id": 4435,
    "lesson": "High-Risk Momentum Watchlist: 1h to 8h needs more samples before changing rules.",
    "median_return_pct": -13.607965638422492,
    "positive_rate": 0.0,
    "sample_count": 2,
    "source_label": "High-Risk Momentum Watchlist",
    "verdict": "Too Small Sample",
    "worst_return_pct": -27.215931276844984
  },
  {
    "average_return_pct": 0.0,
    "best_return_pct": 0.0,
    "created_at": "2026-05-14T00:16:46+00:00",
    "entry_delay": "1h",
    "exit_horizon": "4h",
    "id": 4434,
    "lesson": "High-Risk Momentum Watchlist: 1h to 4h needs more samples before changing rules.",
    "median_return_pct": 0.0,
    "positive_rate": 0.0,
    "sample_count": 2,
    "source_label": "High-Risk Momentum Watchlist",
    "verdict": "Too Small Sample",
    "worst_return_pct": 0.0
  },
  {
    "average_return_pct": 0.0,
    "best_return_pct": 0.0,
    "created_at": "2026-05-14T00:16:46+00:00",
    "entry_delay": "1h",
    "exit_horizon": "2h",
    "id": 4433,
    "lesson": "High-Risk Momentum Watchlist: 1h to 2h needs more samples before changing rules.",
    "median_return_pct": 0.0,
    "positive_rate": 0.0,
    "sample_count": 2,
    "source_label": "High-Risk Momentum Watchlist",
    "verdict": "Too Small Sample",
    "worst_return_pct": 0.0
  },
  {
    "average_return_pct": -18.04537925884245,
    "best_return_pct": -11.178614823815314,
    "created_at": "2026-05-14T00:16:46+00:00",
    "entry_delay": "1h",
    "exit_horizon": "24h",
    "id": 4432,
    "lesson": "High-Risk Momentum Watchlist: 1h to 24h needs more samples before changing rules.",
    "median_return_pct": -18.04537925884245,
    "positive_rate": 0.0,
    "sample_count": 2,
    "source_label": "High-Risk Momentum Watchlist",
    "verdict": "Too Small Sample",
    "worst_return_pct": -24.91214369386958
  },
  {
    "average_return_pct": 9.287531806615778,
    "best_return_pct": 18.575063613231556,
    "created_at": "2026-05-14T00:16:46+00:00",
    "entry_delay": "15m",
    "exit_horizon": "8h",
    "id": 4431,
    "lesson": "High-Risk Momentum Watchlist: 15m to 8h needs more samples before changing rules.",
    "median_return_pct": 9.287531806615778,
    "positive_rate": 0.5,
    "sample_count": 2,
    "source_label": "High-Risk Momentum Watchlist",
    "verdict": "Too Small Sample",
    "worst_return_pct": 0.0
  },
  {
    "average_return_pct": 31.456743002544542,
    "best_return_pct": 62.913486005089084,
    "created_at": "2026-05-14T00:16:46+00:00",
    "entry_delay": "15m",
    "exit_horizon": "4h",
    "id": 4430,
    "lesson": "High-Risk Momentum Watchlist: 15m to 4h needs more samples before changing rules.",
    "median_return_pct": 31.456743002544542,
    "positive_rate": 0.5,
    "sample_count": 2,
    "source_label": "High-Risk Momentum Watchlist",
    "verdict": "Too Small Sample",
    "worst_return_pct": 0.0
  },
  {
    "average_return_pct": 0.0,
    "best_return_pct": 0.0,
    "created_at": "2026-05-14T00:16:46+00:00",
    "entry_delay": "15m",
    "exit_horizon": "30m",
    "id": 4429,
    "lesson": "High-Risk Momentum Watchlist: 15m to 30m needs more samples before changing rules.",
    "median_return_pct": 0.0,
    "positive_rate": 0.0,
    "sample_count": 2,
    "source_label": "High-Risk Momentum Watchlist",
    "verdict": "Too Small Sample",
    "worst_return_pct": 0.0
  },
  {
    "average_return_pct": 31.456743002544542,
    "best_return_pct": 62.913486005089084,
    "created_at": "2026-05-14T00:16:46+00:00",
    "entry_delay": "15m",
    "exit_horizon": "2h",
    "id": 4428,
    "lesson": "High-Risk Momentum Watchlist: 15m to 2h needs more samples before changing rules.",
    "median_return_pct": 31.456743002544542,
    "positive_rate": 0.5,
    "sample_count": 2,
    "source_label": "High-Risk Momentum Watchlist",
    "verdict": "Too Small Sample",
    "worst_return_pct": 0.0
  },
  {
    "average_return_pct": 5.574814725496929,
    "best_return_pct": 22.328244274809173,
    "created_at": "2026-05-14T00:16:46+00:00",
    "entry_delay": "15m",
    "exit_horizon": "24h",
    "id": 4427,
    "lesson": "High-Risk Momentum Watchlist: 15m to 24h needs more samples before changing rules.",
    "median_return_pct": 5.574814725496929,
    "positive_rate": 0.5,
    "sample_count": 2,
    "source_label": "High-Risk Momentum Watchlist",
    "verdict": "Too Small Sample",
    "worst_return_pct": -11.178614823815314
  },
  {
    "average_return_pct": 31.456743002544542,
    "best_return_pct": 62.913486005089084,
    "created_at": "2026-05-14T00:16:46+00:00",
    "entry_delay": "15m",
    "exit_horizon": "1h",
    "id": 4426,
    "lesson": "High-Risk Momentum Watchlist: 15m to 1h needs more samples before changing rules.",
    "median_return_pct": 31.456743002544542,
    "positive_rate": 0.5,
    "sample_count": 2,
    "source_label": "High-Risk Momentum Watchlist",
    "verdict": "Too Small Sample",
    "worst_return_pct": 0.0
  }
]